lowatt_grdf/__init__.py
lowatt_grdf/api.py
lowatt_grdf/main.py
lowatt_grdf/models.py
lowatt_grdf/py.typed
lowatt_grdf-2.5.0.dist-info/METADATA
lowatt_grdf-2.5.0.dist-info/WHEEL
lowatt_grdf-2.5.0.dist-info/entry_points.txt
lowatt_grdf-2.5.0.dist-info/licenses/LICENSE
lowatt_grdf-2.5.0.dist-info/RECORD
