Metadata-Version: 2.4
Name: lowatt-grdf
Version: 2.5.0
Summary: Python client for GRDF ADICT API
Project-URL: Source, https://github.com/lowatt/lowatt-grdf
Project-URL: Tracker, https://github.com/lowatt/lowatt-grdf/issues
Author-email: Lowatt <info@lowatt.fr>
License: GPLv3
License-File: LICENSE
Classifier: Development Status :: 5 - Production/Stable
Classifier: Environment :: Console
Classifier: License :: OSI Approved :: MIT License
Classifier: Operating System :: OS Independent
Classifier: Programming Language :: Python :: 3
Classifier: Programming Language :: Python :: 3 :: Only
Classifier: Programming Language :: Python :: 3.9
Classifier: Programming Language :: Python :: 3.10
Classifier: Programming Language :: Python :: 3.11
Classifier: Topic :: System :: Archiving :: Mirroring
Classifier: Typing :: Typed
Requires-Python: >=3.9
Requires-Dist: attrs
Requires-Dist: cattrs
Requires-Dist: click
Requires-Dist: ndjson
Requires-Dist: requests
Requires-Dist: rich
Provides-Extra: test
Requires-Dist: pytest; extra == 'test'
Requires-Dist: pytest-cov; extra == 'test'
Requires-Dist: responses; extra == 'test'
Provides-Extra: typing
Requires-Dist: mypy; extra == 'typing'
Requires-Dist: types-requests; extra == 'typing'
